[
  {
    "id": 0,
    "title": "Статут організації",
    "text": [
      {
        "text": "",
        "list": []
      }
    ],
    "imgUrl": [
      "сканирование0003.jpg",
      "сканирование0004.jpg",
      "сканирование0007.jpg",
      "сканирование0008.jpg",
      "сканирование0009.jpg",
      "сканирование0010.jpg",
      "сканирование0011.jpg",
      "сканирование0012.jpg",
      "сканирование0013.jpg",
      "сканирование0005.jpg",
      "сканирование0015.jpg",
      "сканирование0016.jpg",
      "сканирование0017.jpg",
      "сканирование0018.jpg",
      "сканирование0014.jpg"
    ]
  },
  {
    "id": 1,
    "title": "Баланс і звіт про фінансові результати",
    "text": [
      {
        "text": "",
        "list": []
      }
    ],
    "imgUrl": [
      "сканирование0019.jpg",
      "сканирование0033.jpg"
    ]
  },
  {
    "id": 2,
    "title": "Інформація про суми благодійних внесків",
    "text": [
      {
        "text": "",
        "list": []
      }
    ],
    "imgUrl": [
      "сканирование0034.jpg"
    ]
  },
  {
    "id": 3,
    "title": "Інформація про майнову базу",
    "text": [
      {
        "text": "",
        "list": []
      }
    ],
    "imgUrl": [
      "сканирование0020.jpg",
      "сканирование0032.jpg",
      "сканирование0022.jpg",
      "сканирование0023.jpg",
      "сканирование0024.jpg",
      "сканирование0025.jpg",
      "сканирование0026.jpg",
      "сканирование0027.jpg",
      "сканирование0028.jpg",
      "сканирование0029.jpg",
      "сканирование0030.jpg",
      "сканирование0031.jpg"
    ]
  },
  {
    "id": 4,
    "title": "Довідка про керівний орган",
    "text": [
      {
        "text": "",
        "list": [
          "1. Красіцька Т.Л. - в 1987 році заснувала та очолила ГОІЧ 'Земляки'.",
          "2. Дятлова Л.І. - з 2008 року  пенсіонер, волонтер в організації.",
          "3. Дондукова Г.Ю.- з 2008 року пенсіонер, волонтер в організації.",
          "4. Сухорукова О.М. - з 2008 року пенсіонер, волонтер в організації.",
          "5. Цибульська Т.А. - з 2008 року пенсіонер, волонтер в організації.",
          "6. Шелепова Н.С. - з 2008 року пенсіонер, волонтер в організації.",
          "7. Федосенко В.В. - з 2008 року працює в Чорнобиль спец.комбінат. Старш.майстер Елекроцеху. Волонтер в організації."
        ]
      }
    ],
    "imgUrl": [
      "leaders.png"
    ]
  },
  {
    "id": 5,
    "title": "Перспективні плани",
    "text": [
      {
        "text": "",
        "list": []
      }
    ],
    "imgUrl": [
      "selection_065.png",
      "selection_066.png",
      "selection_067.png",
      "selection_068.png",
      "selection_069.png",
      "selection_070.png",
      "selection_071.png",
      "selection_072.png",
      "selection_073.png",
      "selection_074.png",
      "selection_075.png",
      "selection_076.png",
      "selection_077.png",
      "selection_078.png"
    ]
  }
]



